setup.cfg
setup.py
src/twitter/__init__.py
src/twitter.common.string.egg-info/PKG-INFO
src/twitter.common.string.egg-info/SOURCES.txt
src/twitter.common.string.egg-info/dependency_links.txt
src/twitter.common.string.egg-info/namespace_packages.txt
src/twitter.common.string.egg-info/requires.txt
src/twitter.common.string.egg-info/top_level.txt
src/twitter.common.string.egg-info/zip-safe
src/twitter/common/__init__.py
src/twitter/common/string/__init__.py
src/twitter/common/string/scanf.py